codemetrics_cli/__init__.py
codemetrics_cli/__main__.py
codemetrics_cli/metrics.py
codemetrics_cli-0.1.4.dist-info/METADATA
codemetrics_cli-0.1.4.dist-info/WHEEL
codemetrics_cli-0.1.4.dist-info/entry_points.txt
codemetrics_cli-0.1.4.dist-info/licenses/LICENSE
codemetrics_cli-0.1.4.dist-info/RECORD
